LICENSE
README.md
darp.py
setup.py
darp.egg-info/PKG-INFO
darp.egg-info/SOURCES.txt
darp.egg-info/dependency_links.txt
darp.egg-info/top_level.txt